expressive/__init__.py
expressive/analyze.py
expressive/codegen.py
expressive/config.py
expressive/data.py
expressive/expressive.py
expressive/messaging.py
expressive/parallel.py
expressive/parsers.py
expressive/schemas.py
expressive/unset.py
expressive/version.py
expressive-3.10.20250908.dist-info/licenses/LICENSE.txt
expressive-3.10.20250908.dist-info/METADATA
expressive-3.10.20250908.dist-info/WHEEL
expressive-3.10.20250908.dist-info/top_level.txt
expressive-3.10.20250908.dist-info/RECORD
