Metadata-Version: 2.4
Name: expressive
Version: 3.10.20250908
Summary: A library for quickly applying symbolic expressions to NumPy arrays
Home-page: https://gitlab.com/expressive-py/expressive
Maintainer: Russell Fordyce
License: Apache License 2.0
Keywords: sympy numba numpy codegen
Classifier: Development Status :: 4 - Beta
Classifier: Operating System :: POSIX :: Linux
Classifier: Programming Language :: Python
Classifier: Programming Language :: Python :: 3
Classifier: Programming Language :: Python :: 3 :: Only
Classifier: Programming Language :: Python :: 3.7
Classifier: Programming Language :: Python :: 3.8
Classifier: Programming Language :: Python :: 3.9
Classifier: Programming Language :: Python :: 3.10
Classifier: Programming Language :: Python :: 3.11
Classifier: Programming Language :: Python :: 3.12
Classifier: Programming Language :: Python :: 3.13
Classifier: Topic :: Scientific/Engineering
Classifier: Topic :: Software Development :: Code Generators
Classifier: Topic :: Software Development :: Compilers
Requires-Python: >=3.7
License-File: LICENSE.txt
Requires-Dist: sympy>=1.6
Requires-Dist: numpy>=1.21.6
Requires-Dist: numba>=0.53.0
Dynamic: classifier
Dynamic: description
Dynamic: description-content-type
Dynamic: home-page
Dynamic: keywords
Dynamic: license
Dynamic: license-file
Dynamic: maintainer
Dynamic: requires-dist
Dynamic: requires-python
Dynamic: summary
